PocketTRC20/CLI.py
PocketTRC20/__init__.py
PocketTRC20/__main__.py
PocketTRC20/config.py
PocketTRC20/scanner.py
pockettrc20-1.0.6.dist-info/licenses/LICENSE
pockettrc20-1.0.6.dist-info/METADATA
pockettrc20-1.0.6.dist-info/WHEEL
pockettrc20-1.0.6.dist-info/entry_points.txt
pockettrc20-1.0.6.dist-info/top_level.txt
pockettrc20-1.0.6.dist-info/RECORD
