Metadata-Version: 2.4
Name: PocketTRC20
Version: 1.0.6
Summary: Python TRON Blockchain Explorer
Home-page: https://github.com/codelao/PocketTRC20
Author: Lao
License: MIT
License-File: LICENSE
Requires-Dist: requests>=2.28.2
Requires-Dist: colorama>=0.4.6
Requires-Dist: progress>=1.6
Dynamic: author
Dynamic: description
Dynamic: description-content-type
Dynamic: home-page
Dynamic: license
Dynamic: license-file
Dynamic: requires-dist
Dynamic: summary
